pyhanko/__init__.py
pyhanko/__main__.py
pyhanko/keys.py
pyhanko/py.typed
pyhanko/stamp.py
pyhanko/version.py
pyhanko/cli/__init__.py
pyhanko/cli/_ctx.py
pyhanko/cli/_root.py
pyhanko/cli/_trust.py
pyhanko/cli/config.py
pyhanko/cli/plugin_api.py
pyhanko/cli/runtime.py
pyhanko/cli/utils.py
pyhanko/cli/commands/__init__.py
pyhanko/cli/commands/crypt.py
pyhanko/cli/commands/fields.py
pyhanko/cli/commands/stamp.py
pyhanko/cli/commands/signing/__init__.py
pyhanko/cli/commands/signing/pkcs11_cli.py
pyhanko/cli/commands/signing/plugin.py
pyhanko/cli/commands/signing/simple.py
pyhanko/cli/commands/signing/utils.py
pyhanko/cli/commands/validation/__init__.py
pyhanko/cli/commands/validation/ltv.py
pyhanko/cli/commands/validation/validate.py
pyhanko/config/__init__.py
pyhanko/config/api.py
pyhanko/config/errors.py
pyhanko/config/local_keys.py
pyhanko/config/logging.py
pyhanko/config/pkcs11.py
pyhanko/config/trust.py
pyhanko/generated/__init__.py
pyhanko/generated/xml.py
pyhanko/generated/etsi/__init__.py
pyhanko/generated/etsi/ts_11910202.py
pyhanko/generated/etsi/ts_119612.py
pyhanko/generated/etsi/xades.py
pyhanko/generated/w3c/__init__.py
pyhanko/generated/w3c/xmldsig_core.py
pyhanko/pdf_utils/__init__.py
pyhanko/pdf_utils/barcodes.py
pyhanko/pdf_utils/content.py
pyhanko/pdf_utils/embed.py
pyhanko/pdf_utils/extensions.py
pyhanko/pdf_utils/filters.py
pyhanko/pdf_utils/generic.py
pyhanko/pdf_utils/images.py
pyhanko/pdf_utils/incremental_writer.py
pyhanko/pdf_utils/layout.py
pyhanko/pdf_utils/misc.py
pyhanko/pdf_utils/qr.py
pyhanko/pdf_utils/reader.py
pyhanko/pdf_utils/rw_common.py
pyhanko/pdf_utils/text.py
pyhanko/pdf_utils/writer.py
pyhanko/pdf_utils/xref.py
pyhanko/pdf_utils/crypt/__init__.py
pyhanko/pdf_utils/crypt/_iso32004_asn1.py
pyhanko/pdf_utils/crypt/_legacy.py
pyhanko/pdf_utils/crypt/_saslprep.py
pyhanko/pdf_utils/crypt/_util.py
pyhanko/pdf_utils/crypt/api.py
pyhanko/pdf_utils/crypt/cred_ser.py
pyhanko/pdf_utils/crypt/filter_mixins.py
pyHanko-0.25.3.dist-info/LICENSE
pyHanko-0.25.3.dist-info/LICENSE.PyPDF2
pyHanko-0.25.3.dist-info/METADATA
pyHanko-0.25.3.dist-info/WHEEL
pyHanko-0.25.3.dist-info/entry_points.txt
pyHanko-0.25.3.dist-info/top_level.txt
pyHanko-0.25.3.dist-info/RECORD
