Metadata-Version: 2.1
Name: pyHanko
Version: 0.25.3
Summary: Tools for stamping and signing PDF files
Author-email: Matthias Valvekens <dev@mvalvekens.be>
Maintainer-email: Matthias Valvekens <dev@mvalvekens.be>
License: MIT
Project-URL: Homepage, https://github.com/MatthiasValvekens/pyHanko
Project-URL: Documentation, https://pyhanko.readthedocs.io/
Project-URL: Changes, https://pyhanko.readthedocs.io/en/latest/changelog.html
Project-URL: Source Code, https://github.com/MatthiasValvekens/pyHanko
Project-URL: Issue Tracker, https://github.com/MatthiasValvekens/pyHanko/issues
Keywords: signature,pdf,pades,digital-signature,pkcs11
Classifier: Development Status :: 4 - Beta
Classifier: Intended Audience :: Developers
Classifier: Operating System :: OS Independent
Classifier: License :: OSI Approved :: MIT License
Classifier: Programming Language :: Python :: 3
Classifier: Programming Language :: Python :: 3.8
Classifier: Programming Language :: Python :: 3.9
Classifier: Programming Language :: Python :: 3.10
Classifier: Programming Language :: Python :: 3.11
Classifier: Programming Language :: Python :: 3.12
Classifier: Programming Language :: Python :: 3.13
Classifier: Topic :: Security :: Cryptography
Classifier: Topic :: Software Development :: Libraries :: Python Modules
Requires-Python: >=3.8
License-File: LICENSE
License-File: pyhanko/pdf_utils/LICENSE.PyPDF2
Requires-Dist: asn1crypto>=1.5.1
Requires-Dist: qrcode>=7.3.1
Requires-Dist: tzlocal>=4.3
Requires-Dist: pyhanko-certvalidator<0.27,>=0.26.5
Requires-Dist: click>=8.1.3
Requires-Dist: requests>=2.31.0
Requires-Dist: pyyaml>=6.0
Requires-Dist: cryptography>=43.0.3
Provides-Extra: extra-pubkey-algs
Requires-Dist: oscrypto>=1.2.1; extra == "extra-pubkey-algs"
Provides-Extra: xmp
Requires-Dist: defusedxml~=0.7.1; extra == "xmp"
Provides-Extra: opentype
Requires-Dist: fonttools>=4.33.3; extra == "opentype"
Requires-Dist: uharfbuzz<0.43.0,>=0.25.0; extra == "opentype"
Provides-Extra: image-support
Requires-Dist: Pillow>=7.2.0; extra == "image-support"
Requires-Dist: python-barcode==0.15.1; extra == "image-support"
Provides-Extra: pkcs11
Requires-Dist: python-pkcs11~=0.7.0; extra == "pkcs11"
Provides-Extra: async-http
Requires-Dist: aiohttp<3.12,>=3.9; extra == "async-http"
Provides-Extra: etsi
Requires-Dist: xsdata<25.0,>=24.4; extra == "etsi"
Provides-Extra: testing-basic
Requires-Dist: pytest>=6.1.1; extra == "testing-basic"
Requires-Dist: requests-mock>=1.8.0; extra == "testing-basic"
Requires-Dist: freezegun>=1.1.0; extra == "testing-basic"
Requires-Dist: pytest-asyncio==0.24.0; extra == "testing-basic"
Requires-Dist: certomancer<0.13,>=0.12.3; extra == "testing-basic"
Requires-Dist: pytest-cov<6.1,>=4.0; extra == "testing-basic"
Requires-Dist: backports.zoneinfo[tzdata]; python_version < "3.9" and extra == "testing-basic"
Provides-Extra: testing
Requires-Dist: pyHanko[async-http,extra-pubkey-algs,image-support,opentype,pkcs11,testing-basic,xmp]; extra == "testing"
Requires-Dist: pyHanko[etsi]; extra == "testing"
Requires-Dist: pytest-aiohttp~=1.0.4; extra == "testing"
Requires-Dist: certomancer-csc-dummy==0.3.0; extra == "testing"
Provides-Extra: live-test
Requires-Dist: pyHanko[async-http,extra-pubkey-algs,testing-basic,xmp]; extra == "live-test"
Requires-Dist: pytest-aiohttp~=1.0.4; extra == "live-test"
Requires-Dist: certomancer-csc-dummy==0.3.0; extra == "live-test"
Requires-Dist: certomancer[web-api]<0.13,>=0.12.3; extra == "live-test"
Requires-Dist: pytest-cov<6.1,>=4.0; extra == "live-test"
Provides-Extra: mypy
Requires-Dist: pyHanko[async-http,etsi,extra-pubkey-algs,image-support,opentype,pkcs11,xmp]; extra == "mypy"
Requires-Dist: types-requests; extra == "mypy"
Requires-Dist: types-python-dateutil; extra == "mypy"
Requires-Dist: types-PyYAML; extra == "mypy"
Requires-Dist: types-tzlocal; extra == "mypy"
Provides-Extra: docs
Requires-Dist: sphinx; extra == "docs"
Requires-Dist: sphinx-rtd-theme; extra == "docs"
